colorblind_pdf/__init__.py
colorblind_pdf/colorblind_pdf.py
colorblind_pdf-0.2.0.dist-info/LICENSE
colorblind_pdf-0.2.0.dist-info/METADATA
colorblind_pdf-0.2.0.dist-info/WHEEL
colorblind_pdf-0.2.0.dist-info/entry_points.txt
colorblind_pdf-0.2.0.dist-info/top_level.txt
colorblind_pdf-0.2.0.dist-info/RECORD
