Metadata-Version: 2.1
Name: colorblind-pdf
Version: 0.2.0
Summary: A package to process PDFs for testing colorblind accessibility.
Author-email: David Völgyes <david.volgyes@ieee.org>
Project-URL: Home, https://github.com/dvolgyes/colorblind_pdf/
Requires-Python: >=3.10
License-File: LICENSE
Requires-Dist: click ~=8.1.7
Requires-Dist: PyMuPDF ~=1.23
Requires-Dist: Pillow ~=10.1
Requires-Dist: numpy ~=1.26.2
Requires-Dist: loguru ~=0.7.2
Requires-Dist: opencv-python ~=4.8.1.78
Requires-Dist: colorblind
